optimum/rbln/__init__.py
optimum/rbln/__version__.py
optimum/rbln/cli.py
optimum/rbln/configuration_utils.py
optimum/rbln/modeling.py
optimum/rbln/modeling_base.py
optimum/rbln/diffusers/__init__.py
optimum/rbln/diffusers/modeling_diffusers.py
optimum/rbln/diffusers/configurations/__init__.py
optimum/rbln/diffusers/configurations/models/__init__.py
optimum/rbln/diffusers/configurations/models/configuration_autoencoder_kl.py
optimum/rbln/diffusers/configurations/models/configuration_autoencoder_kl_cosmos.py
optimum/rbln/diffusers/configurations/models/configuration_autoencoder_kl_temporal_decoder.py
optimum/rbln/diffusers/configurations/models/configuration_controlnet.py
optimum/rbln/diffusers/configurations/models/configuration_prior_transformer.py
optimum/rbln/diffusers/configurations/models/configuration_transformer_cosmos.py
optimum/rbln/diffusers/configurations/models/configuration_transformer_sd3.py
optimum/rbln/diffusers/configurations/models/configuration_unet_2d_condition.py
optimum/rbln/diffusers/configurations/models/configuration_unet_spatio_temporal_condition.py
optimum/rbln/diffusers/configurations/models/configuration_vq_model.py
optimum/rbln/diffusers/configurations/pipelines/__init__.py
optimum/rbln/diffusers/configurations/pipelines/configuration_controlnet.py
optimum/rbln/diffusers/configurations/pipelines/configuration_cosmos.py
optimum/rbln/diffusers/configurations/pipelines/configuration_kandinsky2_2.py
optimum/rbln/diffusers/configurations/pipelines/configuration_stable_diffusion.py
optimum/rbln/diffusers/configurations/pipelines/configuration_stable_diffusion_3.py
optimum/rbln/diffusers/configurations/pipelines/configuration_stable_diffusion_xl.py
optimum/rbln/diffusers/configurations/pipelines/configuration_stable_video_diffusion.py
optimum/rbln/diffusers/models/__init__.py
optimum/rbln/diffusers/models/controlnet.py
optimum/rbln/diffusers/models/autoencoders/__init__.py
optimum/rbln/diffusers/models/autoencoders/autoencoder_kl.py
optimum_rbln-0.10.0.post1.dist-info/METADATA
optimum_rbln-0.10.0.post1.dist-info/WHEEL
optimum_rbln-0.10.0.post1.dist-info/entry_points.txt
optimum_rbln-0.10.0.post1.dist-info/licenses/LICENSE
optimum_rbln-0.10.0.post1.dist-info/RECORD
