Metadata-Version: 2.4
Name: optimum-rbln
Version: 0.10.0.post1
Summary: Optimum RBLN is the interface between the HuggingFace Transformers and Diffusers libraries and RBLN accelerators. It provides a set of tools enabling easy model loading and inference on single and multiple rbln device settings for different downstream tasks.
Project-URL: Homepage, https://rebellions.ai
Project-URL: Documentation, https://docs.rbln.ai
Project-URL: Repository, https://github.com/rbln-sw/optimum-rbln
Author-email: "Rebellions Inc." <support@rebellions.ai>
License-Expression: Apache-2.0
License-File: LICENSE
Keywords: atom,diffusers,inference,rbln,rebel,transformers
Classifier: Development Status :: 2 - Pre-Alpha
Classifier: Intended Audience :: Developers
Classifier: Intended Audience :: Education
Classifier: Intended Audience :: Science/Research
Classifier: License :: OSI Approved :: Apache Software License
Classifier: Operating System :: POSIX :: Linux
Classifier: Programming Language :: Python :: 3 :: Only
Classifier: Programming Language :: Python :: 3.9
Classifier: Programming Language :: Python :: 3.10
Classifier: Programming Language :: Python :: 3.11
Classifier: Programming Language :: Python :: 3.12
Classifier: Programming Language :: Python :: 3.13
Classifier: Topic :: Scientific/Engineering :: Artificial Intelligence
Requires-Python: <3.14,>=3.9
Requires-Dist: accelerate>=1.0.1
Requires-Dist: diffusers==0.36.0
Requires-Dist: packaging>=24.1
Requires-Dist: torch==2.8.0
Requires-Dist: torchaudio<=2.8.0
Requires-Dist: torchvision<=0.23.0
Requires-Dist: transformers==4.57.3
